{
    "copyright": "\u00a9 Love and Radio LLC",
    "description": "\n      What\u2019s your secret? Listen as anonymous callers from across the globe share what is hidden in their lives. It\u2019s both a voyeuristic and affirming experience.\u00a0Leave your own at 1-929-SECRETS (929-732-7387) or\u00a0secretshotline.org.\n    ",
    "feedUrl": "https://rss.art19.com/the-secrets-hotline",
    "generator": "ART19",
    "image": {
        "link": "https://secretshotline.org",
        "title": "The Secrets Hotline",
        "url": "https://content.production.cdn.art19.com/images/bf/04/28/be/bf0428be-c536-4f87-b1a3-044071c2f296/7bee994acbd000f54fdc23688f15800e74a411d9c6473ef8e56b6b20ef5677622e84433d398c845cd38814c7368c56f4b9d9c6b8bd25bfc3950cd3fa37610da4.jpeg"
    },
    "items": [
        {
            "content": "\n        <p>Happy Halloween, everrybody!</p><p><br></p><p>LEAVE A SECRET!</p><p>https://secretshotline.org or 929-SECRETS</p><p><br></p><p>PLAYLIST!</p><p>https://tambien.bandcamp.com/track/fond</p><p>https://tambien.bandcamp.com/track/the-inner-cave</p><p>https://tambien.bandcamp.com/track/caucho</p><p><br></p><p>DONATE!</p><p>https://loveandradio.org/member</p><p><br></p><p>\u00a1SECRETOS EN ESPA\u00d1OL!</p><p>https://canalconfidente.org</p><p>See Privacy Policy at <a href=\"https://art19.com/privacy\" rel=\"noopener noreferrer\" target=\"_blank\">https://art19.com/privacy</a> and California Privacy Notice at <a href=\"https://art19.com/privacy#do-not-sell-my-info\" rel=\"noopener noreferrer\" target=\"_blank\">https://art19.com/privacy#do-not-sell-my-info</a>.</p>\n      ",
            "content:encoded": "\n        <p>Happy Halloween, everrybody!</p><p><br></p><p>LEAVE A SECRET!</p><p>https://secretshotline.org or 929-SECRETS</p><p><br></p><p>PLAYLIST!</p><p>https://tambien.bandcamp.com/track/fond</p><p>https://tambien.bandcamp.com/track/the-inner-cave</p><p>https://tambien.bandcamp.com/track/caucho</p><p><br></p><p>DONATE!</p><p>https://loveandradio.org/member</p><p><br></p><p>\u00a1SECRETOS EN ESPA\u00d1OL!</p><p>https://canalconfidente.org</p><p>See Privacy Policy at <a href=\"https://art19.com/privacy\" rel=\"noopener noreferrer\" target=\"_blank\">https://art19.com/privacy</a> and California Privacy Notice at <a href=\"https://art19.com/privacy#do-not-sell-my-info\" rel=\"noopener noreferrer\" target=\"_blank\">https://art19.com/privacy#do-not-sell-my-info</a>.</p>\n      ",
            "content:encodedSnippet": "Happy Halloween, everrybody!\n\n\nLEAVE A SECRET!\nhttps://secretshotline.org or 929-SECRETS\n\n\nPLAYLIST!\nhttps://tambien.bandcamp.com/track/fond\nhttps://tambien.bandcamp.com/track/the-inner-cave\nhttps://tambien.bandcamp.com/track/caucho\n\n\nDONATE!\nhttps://loveandradio.org/member\n\n\n\u00a1SECRETOS EN ESPA\u00d1OL!\nhttps://canalconfidente.org\nSee Privacy Policy at https://art19.com/privacy and California Privacy Notice at https://art19.com/privacy#do-not-sell-my-info.",
            "contentSnippet": "Happy Halloween, everrybody!\n\n\nLEAVE A SECRET!\nhttps://secretshotline.org or 929-SECRETS\n\n\nPLAYLIST!\nhttps://tambien.bandcamp.com/track/fond\nhttps://tambien.bandcamp.com/track/the-inner-cave\nhttps://tambien.bandcamp.com/track/caucho\n\n\nDONATE!\nhttps://loveandradio.org/member\n\n\n\u00a1SECRETOS EN ESPA\u00d1OL!\nhttps://canalconfidente.org\nSee Privacy Policy at https://art19.com/privacy and California Privacy Notice at https://art19.com/privacy#do-not-sell-my-info.",
            "enclosure": {
                "length": "14717178",
                "type": "audio/mpeg",
                "url": "https://2.gum.fm/rss.art19.com/episodes/b0d41e45-f22a-4895-a8ab-9d017ad1096b.mp3?rss_browser=BAhJIg9yc3MtcGFyc2VyBjoGRVQ%3D--42d668516e215326a0c0e36404173d504b339a70"
            },
            "guid": "gid://art19-episode-locator/V0/kMJWH0NafIrP6SscvkSoau1ZJHGeZAlaPdfjXAPD73o",
            "isoDate": "2023-10-31T14:53:26.000Z",
            "itunes": {
                "duration": "00:15:19",
                "episode": "56",
                "episodeType": "full",
                "explicit": "yes",
                "image": "https://content.production.cdn.art19.com/images/bf/04/28/be/bf0428be-c536-4f87-b1a3-044071c2f296/7bee994acbd000f54fdc23688f15800e74a411d9c6473ef8e56b6b20ef5677622e84433d398c845cd38814c7368c56f4b9d9c6b8bd25bfc3950cd3fa37610da4.jpeg",
                "season": "3",
                "summary": "Happy Halloween, everrybody!\n\n\n\nLEAVE A SECRET!\n\nhttps://secretshotline.org or 929-SECRETS\n\n\n\nPLAYLIST!\n\nhttps://tambien.bandcamp.com/track/fond\n\nhttps://tambien.bandcamp.com/track/the-inner-cave\n\nhttps://tambien.bandcamp.com/track/caucho\n\n\n\nDONATE!\n\nhttps://loveandradio.org/member\n\n\n\n\u00a1SECRETOS EN ESPA\u00d1OL!\n\nhttps://canalconfidente.org"
            },
            "link": "https://art19.com/shows/the-secrets-hotline/episodes/b0d41e45-f22a-4895-a8ab-9d017ad1096b",
            "pubDate": "Tue, 31 Oct 2023 14:53:26 -0000",
            "title": "Fear",
            "entities": {
                "DATE": [
                    "Halloween"
                ],
                "ORG": [
                    "everrybody!LEAVE A"
                ],
                "CARDINAL": [
                    "929-SECRETSPLAYLIST!https://tambien.bandcamp.com"
                ],
                "GPE": [
                    "California"
                ]
            }
        },
        {
            "content": "\n        <p>LEAVE A SECRET!</p><p>https://secretshotline.org or 929-SECRETS</p><p><br></p><p>PLAYLIST!</p><p>https://tambien.bandcamp.com/track/convoy</p><p>https://ab-pulsemandaladistantfiresburning.bandcamp.com/album/r-abacus-lndr</p><p>https://tambien.bandcamp.com/album/arom-ticas</p><p>https://lashermanas.bandcamp.com/track/plasmoide-2</p><p><br></p><p>DONATE!</p><p>https://loveandradio.org/member</p><p><br></p><p>\u00a1SECRETOS EN ESPA\u00d1OL!</p><p>https://canalconfidente.org</p><p>See Privacy Policy at <a href=\"https://art19.com/privacy\" rel=\"noopener noreferrer\" target=\"_blank\">https://art19.com/privacy</a> and California Privacy Notice at <a href=\"https://art19.com/privacy#do-not-sell-my-info\" rel=\"noopener noreferrer\" target=\"_blank\">https://art19.com/privacy#do-not-sell-my-info</a>.</p>\n      ",
            "content:encoded": "\n        <p>LEAVE A SECRET!</p><p>https://secretshotline.org or 929-SECRETS</p><p><br></p><p>PLAYLIST!</p><p>https://tambien.bandcamp.com/track/convoy</p><p>https://ab-pulsemandaladistantfiresburning.bandcamp.com/album/r-abacus-lndr</p><p>https://tambien.bandcamp.com/album/arom-ticas</p><p>https://lashermanas.bandcamp.com/track/plasmoide-2</p><p><br></p><p>DONATE!</p><p>https://loveandradio.org/member</p><p><br></p><p>\u00a1SECRETOS EN ESPA\u00d1OL!</p><p>https://canalconfidente.org</p><p>See Privacy Policy at <a href=\"https://art19.com/privacy\" rel=\"noopener noreferrer\" target=\"_blank\">https://art19.com/privacy</a> and California Privacy Notice at <a href=\"https://art19.com/privacy#do-not-sell-my-info\" rel=\"noopener noreferrer\" target=\"_blank\">https://art19.com/privacy#do-not-sell-my-info</a>.</p>\n      ",
            "content:encodedSnippet": "LEAVE A SECRET!\nhttps://secretshotline.org or 929-SECRETS\n\n\nPLAYLIST!\nhttps://tambien.bandcamp.com/track/convoy\nhttps://ab-pulsemandaladistantfiresburning.bandcamp.com/album/r-abacus-lndr\nhttps://tambien.bandcamp.com/album/arom-ticas\nhttps://lashermanas.bandcamp.com/track/plasmoide-2\n\n\nDONATE!\nhttps://loveandradio.org/member\n\n\n\u00a1SECRETOS EN ESPA\u00d1OL!\nhttps://canalconfidente.org\nSee Privacy Policy at https://art19.com/privacy and California Privacy Notice at https://art19.com/privacy#do-not-sell-my-info.",
            "contentSnippet": "LEAVE A SECRET!\nhttps://secretshotline.org or 929-SECRETS\n\n\nPLAYLIST!\nhttps://tambien.bandcamp.com/track/convoy\nhttps://ab-pulsemandaladistantfiresburning.bandcamp.com/album/r-abacus-lndr\nhttps://tambien.bandcamp.com/album/arom-ticas\nhttps://lashermanas.bandcamp.com/track/plasmoide-2\n\n\nDONATE!\nhttps://loveandradio.org/member\n\n\n\u00a1SECRETOS EN ESPA\u00d1OL!\nhttps://canalconfidente.org\nSee Privacy Policy at https://art19.com/privacy and California Privacy Notice at https://art19.com/privacy#do-not-sell-my-info.",
            "enclosure": {
                "length": "14430458",
                "type": "audio/mpeg",
                "url": "https://2.gum.fm/rss.art19.com/episodes/f6a0d905-5f2f-4854-a7d6-d7441b1099c2.mp3?rss_browser=BAhJIg9yc3MtcGFyc2VyBjoGRVQ%3D--42d668516e215326a0c0e36404173d504b339a70"
            },
            "guid": "gid://art19-episode-locator/V0/MxnQG8Cju-nH-ms23AppkRRxth96s8sYgVgItIaQyIs",
            "isoDate": "2023-10-12T13:30:00.000Z",
            "itunes": {
                "duration": "00:15:01",
                "episode": "55",
                "episodeType": "full",
                "explicit": "yes",
                "image": "https://content.production.cdn.art19.com/images/bf/04/28/be/bf0428be-c536-4f87-b1a3-044071c2f296/7bee994acbd000f54fdc23688f15800e74a411d9c6473ef8e56b6b20ef5677622e84433d398c845cd38814c7368c56f4b9d9c6b8bd25bfc3950cd3fa37610da4.jpeg",
                "season": "3",
                "summary": "LEAVE A SECRET!\n\nhttps://secretshotline.org or 929-SECRETS\n\n\n\nPLAYLIST!\n\nhttps://tambien.bandcamp.com/track/convoy\n\nhttps://ab-pulsemandaladistantfiresburning.bandcamp.com/album/r-abacus-lndr\n\nhttps://tambien.bandcamp.com/album/arom-ticas\n\nhttps://lashermanas.bandcamp.com/track/plasmoide-2\n\n\n\nDONATE!\n\nhttps://loveandradio.org/member\n\n\n\n\u00a1SECRETOS EN ESPA\u00d1OL!\n\nhttps://canalconfidente.org\n\n"
            },
            "link": "https://art19.com/shows/the-secrets-hotline/episodes/f6a0d905-5f2f-4854-a7d6-d7441b1099c2",
            "pubDate": "Thu, 12 Oct 2023 13:30:00 -0000",
            "title": "A Keen Sense of De-Reality",
            "entities": {
                "CARDINAL": [
                    "929-SECRETSPLAYLIST!https://tambien.bandcamp.com"
                ],
                "GPE": [
                    "California"
                ]
            }
        },
        {
            "content": "\n        <p>Listeners grapple with the biggest secret of generations: climate change.</p><p><br></p><p>LEAVE A SECRET!</p><p>secretshotline.org or 929-SECRETS</p><p><br></p><p>GENERATION DREAD!</p><p>https://gendread.substack.com/</p><p><br></p><p>PLAYLIST!</p><p>Pulse Mandala &amp; Distant Fires Burning - R Abacus Lndr - Oblivion in Qbit</p><p>Strangebird~Sounds - Lavender River -&nbsp;Surface Dust</p><p>Strangebird~Sounds - Lavender River - Momentarily</p><p>Pulse Mandala &amp; Distant Fires Burning - R Abacus Lndr - Spectroscopycon</p><p>Interspecifics - La Inmanencia del Ser - Reducci\u00f3n</p><p><br></p><p>DONATE!</p><p>https://loveandradio.org/member</p><p><br></p><p>\u00a1SECRETOS EN ESPA\u00d1OL!</p><p>https://canalconfidente.org</p><p>See Privacy Policy at <a href=\"https://art19.com/privacy\" rel=\"noopener noreferrer\" target=\"_blank\">https://art19.com/privacy</a> and California Privacy Notice at <a href=\"https://art19.com/privacy#do-not-sell-my-info\" rel=\"noopener noreferrer\" target=\"_blank\">https://art19.com/privacy#do-not-sell-my-info</a>.</p>\n      ",
            "content:encoded": "\n        <p>Listeners grapple with the biggest secret of generations: climate change.</p><p><br></p><p>LEAVE A SECRET!</p><p>secretshotline.org or 929-SECRETS</p><p><br></p><p>GENERATION DREAD!</p><p>https://gendread.substack.com/</p><p><br></p><p>PLAYLIST!</p><p>Pulse Mandala &amp; Distant Fires Burning - R Abacus Lndr - Oblivion in Qbit</p><p>Strangebird~Sounds - Lavender River -&nbsp;Surface Dust</p><p>Strangebird~Sounds - Lavender River - Momentarily</p><p>Pulse Mandala &amp; Distant Fires Burning - R Abacus Lndr - Spectroscopycon</p><p>Interspecifics - La Inmanencia del Ser - Reducci\u00f3n</p><p><br></p><p>DONATE!</p><p>https://loveandradio.org/member</p><p><br></p><p>\u00a1SECRETOS EN ESPA\u00d1OL!</p><p>https://canalconfidente.org</p><p>See Privacy Policy at <a href=\"https://art19.com/privacy\" rel=\"noopener noreferrer\" target=\"_blank\">https://art19.com/privacy</a> and California Privacy Notice at <a href=\"https://art19.com/privacy#do-not-sell-my-info\" rel=\"noopener noreferrer\" target=\"_blank\">https://art19.com/privacy#do-not-sell-my-info</a>.</p>\n      ",
            "content:encodedSnippet": "Listeners grapple with the biggest secret of generations: climate change.\n\n\nLEAVE A SECRET!\nsecretshotline.org or 929-SECRETS\n\n\nGENERATION DREAD!\nhttps://gendread.substack.com/\n\n\nPLAYLIST!\nPulse Mandala & Distant Fires Burning - R Abacus Lndr - Oblivion in Qbit\nStrangebird~Sounds - Lavender River -\u00a0Surface Dust\nStrangebird~Sounds - Lavender River - Momentarily\nPulse Mandala & Distant Fires Burning - R Abacus Lndr - Spectroscopycon\nInterspecifics - La Inmanencia del Ser - Reducci\u00f3n\n\n\nDONATE!\nhttps://loveandradio.org/member\n\n\n\u00a1SECRETOS EN ESPA\u00d1OL!\nhttps://canalconfidente.org\nSee Privacy Policy at https://art19.com/privacy and California Privacy Notice at https://art19.com/privacy#do-not-sell-my-info.",
            "contentSnippet": "Listeners grapple with the biggest secret of generations: climate change.\n\n\nLEAVE A SECRET!\nsecretshotline.org or 929-SECRETS\n\n\nGENERATION DREAD!\nhttps://gendread.substack.com/\n\n\nPLAYLIST!\nPulse Mandala & Distant Fires Burning - R Abacus Lndr - Oblivion in Qbit\nStrangebird~Sounds - Lavender River -\u00a0Surface Dust\nStrangebird~Sounds - Lavender River - Momentarily\nPulse Mandala & Distant Fires Burning - R Abacus Lndr - Spectroscopycon\nInterspecifics - La Inmanencia del Ser - Reducci\u00f3n\n\n\nDONATE!\nhttps://loveandradio.org/member\n\n\n\u00a1SECRETOS EN ESPA\u00d1OL!\nhttps://canalconfidente.org\nSee Privacy Policy at https://art19.com/privacy and California Privacy Notice at https://art19.com/privacy#do-not-sell-my-info.",
            "enclosure": {
                "length": "31686321",
                "type": "audio/mpeg",
                "url": "https://2.gum.fm/rss.art19.com/episodes/9ded4baa-3ece-4104-b5bb-5bea69c29472.mp3?rss_browser=BAhJIg9yc3MtcGFyc2VyBjoGRVQ%3D--42d668516e215326a0c0e36404173d504b339a70"
            },
            "guid": "gid://art19-episode-locator/V0/GnTCXf6brY43Jp99FESGovRHuCGiRMRqwKrQmrEGHj8",
            "isoDate": "2023-09-22T14:00:00.000Z",
            "itunes": {
                "duration": "00:33:00",
                "episode": "54",
                "episodeType": "full",
                "explicit": "yes",
                "image": "https://content.production.cdn.art19.com/images/bf/04/28/be/bf0428be-c536-4f87-b1a3-044071c2f296/7bee994acbd000f54fdc23688f15800e74a411d9c6473ef8e56b6b20ef5677622e84433d398c845cd38814c7368c56f4b9d9c6b8bd25bfc3950cd3fa37610da4.jpeg",
                "season": "3",
                "summary": "Listeners grapple with the biggest secret of generations: climate change.\n\nLEAVE A SECRET!\nsecretshotline.org or 929-SECRETS\n\nGENERATION DREAD!\nhttps://gendread.substack.com/\n\nPLAYLIST!\nPulse Mandala & Distant Fires Burning - R Abacus Lndr - Oblivion in Qbit\nStrangebird~Sounds - Lavender River -  Surface Dust\nStrangebird~Sounds - Lavender River - Momentarily\nPulse Mandala & Distant Fires Burning - R Abacus Lndr - Spectroscopycon\nInterspecifics - La Inmanencia del Ser - Reducci\u00f3n\n\nDONATE!\nhttps://loveandradio.org/member\n\n\u00a1SECRETOS EN ESPA\u00d1OL!\nhttps://canalconfidente.org"
            },
            "link": "https://art19.com/shows/the-secrets-hotline/episodes/9ded4baa-3ece-4104-b5bb-5bea69c29472",
            "pubDate": "Fri, 22 Sep 2023 14:00:00 -0000",
            "title": "Gettin Swole for Climate Change",
            "entities": {
                "FAC": [
                    "QbitStrangebird"
                ],
                "PRODUCT": [
                    "Sounds - Lavender River"
                ],
                "GPE": [
                    "California"
                ]
            }
        },
        {
            "content": "\n        <p>One caller puts some advice from TSH to the test. Plus more!</p><p><br></p><p>LEAVE A SECRET!</p><p>https://secretshotline.org or 1-929-SECRETS</p><p><br></p><p>PLAYLIST!</p><p>https://tambien.bandcamp.com/track/cero</p><p>https://ab-jimmybehan.bandcamp.com/track/leaving-here</p><p>https://ab-jimmybehan.bandcamp.com/track/through-the-trees</p><p>https://audiobulb.bandcamp.com/track/butterflies</p><p><br></p><p>DONATE!</p><p>https://loveandradio.org/member</p><p><br></p><p>\u00a1SECRETOS EN ESPA\u00d1OL!</p><p>https://canalconfidente.org</p><p>See Privacy Policy at <a href=\"https://art19.com/privacy\" rel=\"noopener noreferrer\" target=\"_blank\">https://art19.com/privacy</a> and California Privacy Notice at <a href=\"https://art19.com/privacy#do-not-sell-my-info\" rel=\"noopener noreferrer\" target=\"_blank\">https://art19.com/privacy#do-not-sell-my-info</a>.</p>\n      ",
            "content:encoded": "\n        <p>One caller puts some advice from TSH to the test. Plus more!</p><p><br></p><p>LEAVE A SECRET!</p><p>https://secretshotline.org or 1-929-SECRETS</p><p><br></p><p>PLAYLIST!</p><p>https://tambien.bandcamp.com/track/cero</p><p>https://ab-jimmybehan.bandcamp.com/track/leaving-here</p><p>https://ab-jimmybehan.bandcamp.com/track/through-the-trees</p><p>https://audiobulb.bandcamp.com/track/butterflies</p><p><br></p><p>DONATE!</p><p>https://loveandradio.org/member</p><p><br></p><p>\u00a1SECRETOS EN ESPA\u00d1OL!</p><p>https://canalconfidente.org</p><p>See Privacy Policy at <a href=\"https://art19.com/privacy\" rel=\"noopener noreferrer\" target=\"_blank\">https://art19.com/privacy</a> and California Privacy Notice at <a href=\"https://art19.com/privacy#do-not-sell-my-info\" rel=\"noopener noreferrer\" target=\"_blank\">https://art19.com/privacy#do-not-sell-my-info</a>.</p>\n      ",
            "content:encodedSnippet": "One caller puts some advice from TSH to the test. Plus more!\n\n\nLEAVE A SECRET!\nhttps://secretshotline.org or 1-929-SECRETS\n\n\nPLAYLIST!\nhttps://tambien.bandcamp.com/track/cero\nhttps://ab-jimmybehan.bandcamp.com/track/leaving-here\nhttps://ab-jimmybehan.bandcamp.com/track/through-the-trees\nhttps://audiobulb.bandcamp.com/track/butterflies\n\n\nDONATE!\nhttps://loveandradio.org/member\n\n\n\u00a1SECRETOS EN ESPA\u00d1OL!\nhttps://canalconfidente.org\nSee Privacy Policy at https://art19.com/privacy and California Privacy Notice at https://art19.com/privacy#do-not-sell-my-info.",
            "contentSnippet": "One caller puts some advice from TSH to the test. Plus more!\n\n\nLEAVE A SECRET!\nhttps://secretshotline.org or 1-929-SECRETS\n\n\nPLAYLIST!\nhttps://tambien.bandcamp.com/track/cero\nhttps://ab-jimmybehan.bandcamp.com/track/leaving-here\nhttps://ab-jimmybehan.bandcamp.com/track/through-the-trees\nhttps://audiobulb.bandcamp.com/track/butterflies\n\n\nDONATE!\nhttps://loveandradio.org/member\n\n\n\u00a1SECRETOS EN ESPA\u00d1OL!\nhttps://canalconfidente.org\nSee Privacy Policy at https://art19.com/privacy and California Privacy Notice at https://art19.com/privacy#do-not-sell-my-info.",
            "enclosure": {
                "length": "13155265",
                "type": "audio/mpeg",
                "url": "https://2.gum.fm/rss.art19.com/episodes/be5e8025-c1cc-4963-a620-95674e53c218.mp3?rss_browser=BAhJIg9yc3MtcGFyc2VyBjoGRVQ%3D--42d668516e215326a0c0e36404173d504b339a70"
            },
            "guid": "gid://art19-episode-locator/V0/q_Mtczk8xSEtFNDIBF16Dv645JnPjK3mdGGd01-ahBo",
            "isoDate": "2023-09-07T16:00:00.000Z",
            "itunes": {
                "duration": "00:13:42",
                "episode": "53",
                "episodeType": "full",
                "explicit": "yes",
                "image": "https://content.production.cdn.art19.com/images/bf/04/28/be/bf0428be-c536-4f87-b1a3-044071c2f296/7bee994acbd000f54fdc23688f15800e74a411d9c6473ef8e56b6b20ef5677622e84433d398c845cd38814c7368c56f4b9d9c6b8bd25bfc3950cd3fa37610da4.jpeg",
                "season": "3",
                "summary": "One caller puts some advice from TSH to the test. Plus more!\n\n\n\nLEAVE A SECRET!\n\nhttps://secretshotline.org or 1-929-SECRETS\n\n\n\nPLAYLIST!\n\nhttps://tambien.bandcamp.com/track/cero\n\nhttps://ab-jimmybehan.bandcamp.com/track/leaving-here\n\nhttps://ab-jimmybehan.bandcamp.com/track/through-the-trees\n\nhttps://audiobulb.bandcamp.com/track/butterflies\n\n\n\nDONATE!\n\nhttps://loveandradio.org/member\n\n\n\n\u00a1SECRETOS EN ESPA\u00d1OL!\n\nhttps://canalconfidente.org"
            },
            "link": "https://art19.com/shows/the-secrets-hotline/episodes/be5e8025-c1cc-4963-a620-95674e53c218",
            "pubDate": "Thu, 07 Sep 2023 16:00:00 -0000",
            "title": "What's Behind That Door",
            "entities": {
                "CARDINAL": [
                    "One",
                    "1-929-SECRETSPLAYLIST!https://tambien.bandcamp.com"
                ],
                "ORG": [
                    "TSH"
                ],
                "GPE": [
                    "California"
                ]
            }
        },
        {
            "content": "\n        <p>Sticking it to the Man (ie LinkedIn).</p><p><br></p><p>LEAVE A SECRET!</p><p>https://secretshotline.org or 1-929-SECRETS</p><p><br></p><p>PLAYLIST!</p><p>All tracks from the new album </p><p>Arom\u200b\u00e1\u200bticas by dj + 1 (available on the Tambi\u00e9n label):</p><p>https://tambien.bandcamp.com/album/arom-ticas</p><p>Consuelo</p><p>Menta</p><p>Curuba</p><p>Miel</p><p><br></p><p>DONATE!</p><p>https://loveandradio.org/member</p><p><br></p><p>\u00a1SECRETOS EN ESPA\u00d1OL!</p><p>https://canalconfidente.org</p><p><br></p><p>See Privacy Policy at <a href=\"https://art19.com/privacy\" rel=\"noopener noreferrer\" target=\"_blank\">https://art19.com/privacy</a> and California Privacy Notice at <a href=\"https://art19.com/privacy#do-not-sell-my-info\" rel=\"noopener noreferrer\" target=\"_blank\">https://art19.com/privacy#do-not-sell-my-info</a>.</p>\n      ",
            "content:encoded": "\n        <p>Sticking it to the Man (ie LinkedIn).</p><p><br></p><p>LEAVE A SECRET!</p><p>https://secretshotline.org or 1-929-SECRETS</p><p><br></p><p>PLAYLIST!</p><p>All tracks from the new album </p><p>Arom\u200b\u00e1\u200bticas by dj + 1 (available on the Tambi\u00e9n label):</p><p>https://tambien.bandcamp.com/album/arom-ticas</p><p>Consuelo</p><p>Menta</p><p>Curuba</p><p>Miel</p><p><br></p><p>DONATE!</p><p>https://loveandradio.org/member</p><p><br></p><p>\u00a1SECRETOS EN ESPA\u00d1OL!</p><p>https://canalconfidente.org</p><p><br></p><p>See Privacy Policy at <a href=\"https://art19.com/privacy\" rel=\"noopener noreferrer\" target=\"_blank\">https://art19.com/privacy</a> and California Privacy Notice at <a href=\"https://art19.com/privacy#do-not-sell-my-info\" rel=\"noopener noreferrer\" target=\"_blank\">https://art19.com/privacy#do-not-sell-my-info</a>.</p>\n      ",
            "content:encodedSnippet": "Sticking it to the Man (ie LinkedIn).\n\n\nLEAVE A SECRET!\nhttps://secretshotline.org or 1-929-SECRETS\n\n\nPLAYLIST!\nAll tracks from the new album \nArom\u200b\u00e1\u200bticas by dj + 1 (available on the Tambi\u00e9n label):\nhttps://tambien.bandcamp.com/album/arom-ticas\nConsuelo\nMenta\nCuruba\nMiel\n\n\nDONATE!\nhttps://loveandradio.org/member\n\n\n\u00a1SECRETOS EN ESPA\u00d1OL!\nhttps://canalconfidente.org\n\n\nSee Privacy Policy at https://art19.com/privacy and California Privacy Notice at https://art19.com/privacy#do-not-sell-my-info.",
            "contentSnippet": "Sticking it to the Man (ie LinkedIn).\n\n\nLEAVE A SECRET!\nhttps://secretshotline.org or 1-929-SECRETS\n\n\nPLAYLIST!\nAll tracks from the new album \nArom\u200b\u00e1\u200bticas by dj + 1 (available on the Tambi\u00e9n label):\nhttps://tambien.bandcamp.com/album/arom-ticas\nConsuelo\nMenta\nCuruba\nMiel\n\n\nDONATE!\nhttps://loveandradio.org/member\n\n\n\u00a1SECRETOS EN ESPA\u00d1OL!\nhttps://canalconfidente.org\n\n\nSee Privacy Policy at https://art19.com/privacy and California Privacy Notice at https://art19.com/privacy#do-not-sell-my-info.",
            "enclosure": {
                "length": "13760470",
                "type": "audio/mpeg",
                "url": "https://2.gum.fm/rss.art19.com/episodes/ea97f8da-a254-4980-975e-6b7a75d34ffb.mp3?rss_browser=BAhJIg9yc3MtcGFyc2VyBjoGRVQ%3D--42d668516e215326a0c0e36404173d504b339a70"
            },
            "guid": "gid://art19-episode-locator/V0/u2zL549DS_HYpJHdYTa9NknJ-HOpprMyEX-NfNz26TQ",
            "isoDate": "2023-08-30T23:00:00.000Z",
            "itunes": {
                "duration": "00:14:19",
                "episode": "52",
                "episodeType": "full",
                "explicit": "yes",
                "image": "https://content.production.cdn.art19.com/images/bf/04/28/be/bf0428be-c536-4f87-b1a3-044071c2f296/7bee994acbd000f54fdc23688f15800e74a411d9c6473ef8e56b6b20ef5677622e84433d398c845cd38814c7368c56f4b9d9c6b8bd25bfc3950cd3fa37610da4.jpeg",
                "season": "3",
                "summary": "Sticking it to the Man (ie LinkedIn).\n\n\n\nLEAVE A SECRET!\n\nhttps://secretshotline.org or 1-929-SECRETS\n\n\n\nPLAYLIST!\n\nAll tracks from the new album \n\nArom\u200b\u00e1\u200bticas by dj + 1 (available on the Tambi\u00e9n label):\n\nhttps://tambien.bandcamp.com/album/arom-ticas\n\nConsuelo\n\nMenta\n\nCuruba\n\nMiel\n\n\n\nDONATE!\n\nhttps://loveandradio.org/member\n\n\n\n\u00a1SECRETOS EN ESPA\u00d1OL!\n\nhttps://canalconfidente.org\n\n  "
            },
            "link": "https://art19.com/shows/the-secrets-hotline/episodes/ea97f8da-a254-4980-975e-6b7a75d34ffb",
            "pubDate": "Wed, 30 Aug 2023 23:00:00 -0000",
            "title": "I Have to Buy More Sweaters",
            "entities": {
                "CARDINAL": [
                    "1-929"
                ],
                "PERSON": [
                    "Arom\u200b\u00e1\u200bticas"
                ],
                "ORG": [
                    "Tambi\u00e9n"
                ],
                "GPE": [
                    "California"
                ]
            }
        },
        {
            "content": "\n        <p>Stories that cross generations.</p><p><br></p><p>LEAVE A SECRET!</p><p>https://secretshotline.org or 1-929-SECRETS</p><p><br></p><p>PLAYLIST!</p><p>All tracks from the new album And All Things Begin To Drift by Memory Scale (available on the Audiobulb label):</p><p>https://ab-memoryscale.bandcamp.com/album/and-all-things-begin-to-drift </p><p>Downsizing Tape 2</p><p>The Function of Time</p><p>Apr\u00e8s La Pluie</p><p>Datamedia Northerns (Interlude)</p><p>Anyway River</p><p>A Suivre</p><p><br></p><p>DONATE!</p><p>https://loveandradio.org/member</p><p><br></p><p>\u00a1SECRETOS EN ESPA\u00d1OL!</p><p>https://canalconfidente.org</p><p>See Privacy Policy at <a href=\"https://art19.com/privacy\" rel=\"noopener noreferrer\" target=\"_blank\">https://art19.com/privacy</a> and California Privacy Notice at <a href=\"https://art19.com/privacy#do-not-sell-my-info\" rel=\"noopener noreferrer\" target=\"_blank\">https://art19.com/privacy#do-not-sell-my-info</a>.</p>\n      ",
            "content:encoded": "\n        <p>Stories that cross generations.</p><p><br></p><p>LEAVE A SECRET!</p><p>https://secretshotline.org or 1-929-SECRETS</p><p><br></p><p>PLAYLIST!</p><p>All tracks from the new album And All Things Begin To Drift by Memory Scale (available on the Audiobulb label):</p><p>https://ab-memoryscale.bandcamp.com/album/and-all-things-begin-to-drift </p><p>Downsizing Tape 2</p><p>The Function of Time</p><p>Apr\u00e8s La Pluie</p><p>Datamedia Northerns (Interlude)</p><p>Anyway River</p><p>A Suivre</p><p><br></p><p>DONATE!</p><p>https://loveandradio.org/member</p><p><br></p><p>\u00a1SECRETOS EN ESPA\u00d1OL!</p><p>https://canalconfidente.org</p><p>See Privacy Policy at <a href=\"https://art19.com/privacy\" rel=\"noopener noreferrer\" target=\"_blank\">https://art19.com/privacy</a> and California Privacy Notice at <a href=\"https://art19.com/privacy#do-not-sell-my-info\" rel=\"noopener noreferrer\" target=\"_blank\">https://art19.com/privacy#do-not-sell-my-info</a>.</p>\n      ",
            "content:encodedSnippet": "Stories that cross generations.\n\n\nLEAVE A SECRET!\nhttps://secretshotline.org or 1-929-SECRETS\n\n\nPLAYLIST!\nAll tracks from the new album And All Things Begin To Drift by Memory Scale (available on the Audiobulb label):\nhttps://ab-memoryscale.bandcamp.com/album/and-all-things-begin-to-drift \nDownsizing Tape 2\nThe Function of Time\nApr\u00e8s La Pluie\nDatamedia Northerns (Interlude)\nAnyway River\nA Suivre\n\n\nDONATE!\nhttps://loveandradio.org/member\n\n\n\u00a1SECRETOS EN ESPA\u00d1OL!\nhttps://canalconfidente.org\nSee Privacy Policy at https://art19.com/privacy and California Privacy Notice at https://art19.com/privacy#do-not-sell-my-info.",
            "contentSnippet": "Stories that cross generations.\n\n\nLEAVE A SECRET!\nhttps://secretshotline.org or 1-929-SECRETS\n\n\nPLAYLIST!\nAll tracks from the new album And All Things Begin To Drift by Memory Scale (available on the Audiobulb label):\nhttps://ab-memoryscale.bandcamp.com/album/and-all-things-begin-to-drift \nDownsizing Tape 2\nThe Function of Time\nApr\u00e8s La Pluie\nDatamedia Northerns (Interlude)\nAnyway River\nA Suivre\n\n\nDONATE!\nhttps://loveandradio.org/member\n\n\n\u00a1SECRETOS EN ESPA\u00d1OL!\nhttps://canalconfidente.org\nSee Privacy Policy at https://art19.com/privacy and California Privacy Notice at https://art19.com/privacy#do-not-sell-my-info.",
            "enclosure": {
                "length": "13780532",
                "type": "audio/mpeg",
                "url": "https://2.gum.fm/rss.art19.com/episodes/6944c259-bbec-4ce5-88c8-9545364fab17.mp3?rss_browser=BAhJIg9yc3MtcGFyc2VyBjoGRVQ%3D--42d668516e215326a0c0e36404173d504b339a70"
            },
            "guid": "gid://art19-episode-locator/V0/mivPVoEsgbEtxdlviCS1ZayuNjVhoATT1g2Jssgi8HY",
            "isoDate": "2023-08-17T16:30:39.000Z",
            "itunes": {
                "duration": "00:14:21",
                "episode": "51",
                "episodeType": "full",
                "explicit": "yes",
                "image": "https://content.production.cdn.art19.com/images/bf/04/28/be/bf0428be-c536-4f87-b1a3-044071c2f296/7bee994acbd000f54fdc23688f15800e74a411d9c6473ef8e56b6b20ef5677622e84433d398c845cd38814c7368c56f4b9d9c6b8bd25bfc3950cd3fa37610da4.jpeg",
                "season": "3",
                "summary": "Stories that cross generations.\n\n\n\nLEAVE A SECRET!\n\nhttps://secretshotline.org or 1-929-SECRETS\n\n\n\nPLAYLIST!\n\nAll tracks from the new album And All Things Begin To Drift by Memory Scale (available on the Audiobulb label):\n\nhttps://ab-memoryscale.bandcamp.com/album/and-all-things-begin-to-drift \n\nDownsizing Tape 2\n\nThe Function of Time\n\nApr\u00e8s La Pluie\n\nDatamedia Northerns (Interlude)\n\nAnyway River\n\nA Suivre\n\n\n\nDONATE!\n\nhttps://loveandradio.org/member\n\n\n\n\u00a1SECRETOS EN ESPA\u00d1OL!\n\nhttps://canalconfidente.org"
            },
            "link": "https://art19.com/shows/the-secrets-hotline/episodes/6944c259-bbec-4ce5-88c8-9545364fab17",
            "pubDate": "Thu, 17 Aug 2023 16:30:39 -0000",
            "title": "Family Lore",
            "entities": {
                "CARDINAL": [
                    "1-929"
                ],
                "GPE": [
                    "Audiobulb",
                    "California"
                ],
                "ORG": [
                    "Downsizing Tape 2The Function",
                    "SuivreDONATE!https://loveandradio.org"
                ]
            }
        },
        {
            "content": "\n        <p>LEAVE A SECRET!</p><p>Visit https://secretshotline.org or call 1-929-SECRETS</p><p><br></p><p>MUSIC!</p><p>https://tambien.bandcamp.com/track/l-grimas-de-sangre-ii</p><p>https://ab-isikkural.bandcamp.com/track/winter-in-a-cassette</p><p>https://tambien.bandcamp.com/album/las-olas</p><p>https://tambien.bandcamp.com/track/descomposicion-iv-triple-n</p><p><br></p><p>SUPPORT THE SHOW!</p><p>https://loveandradio.org/member</p><p><br></p><p>\u00a1SECRETOS EN ESPA\u00d1OL!</p><p>https://canalconfidente.org</p><p>See Privacy Policy at <a href=\"https://art19.com/privacy\" rel=\"noopener noreferrer\" target=\"_blank\">https://art19.com/privacy</a> and California Privacy Notice at <a href=\"https://art19.com/privacy#do-not-sell-my-info\" rel=\"noopener noreferrer\" target=\"_blank\">https://art19.com/privacy#do-not-sell-my-info</a>.</p>\n      ",
            "content:encoded": "\n        <p>LEAVE A SECRET!</p><p>Visit https://secretshotline.org or call 1-929-SECRETS</p><p><br></p><p>MUSIC!</p><p>https://tambien.bandcamp.com/track/l-grimas-de-sangre-ii</p><p>https://ab-isikkural.bandcamp.com/track/winter-in-a-cassette</p><p>https://tambien.bandcamp.com/album/las-olas</p><p>https://tambien.bandcamp.com/track/descomposicion-iv-triple-n</p><p><br></p><p>SUPPORT THE SHOW!</p><p>https://loveandradio.org/member</p><p><br></p><p>\u00a1SECRETOS EN ESPA\u00d1OL!</p><p>https://canalconfidente.org</p><p>See Privacy Policy at <a href=\"https://art19.com/privacy\" rel=\"noopener noreferrer\" target=\"_blank\">https://art19.com/privacy</a> and California Privacy Notice at <a href=\"https://art19.com/privacy#do-not-sell-my-info\" rel=\"noopener noreferrer\" target=\"_blank\">https://art19.com/privacy#do-not-sell-my-info</a>.</p>\n      ",
            "content:encodedSnippet": "LEAVE A SECRET!\nVisit https://secretshotline.org or call 1-929-SECRETS\n\n\nMUSIC!\nhttps://tambien.bandcamp.com/track/l-grimas-de-sangre-ii\nhttps://ab-isikkural.bandcamp.com/track/winter-in-a-cassette\nhttps://tambien.bandcamp.com/album/las-olas\nhttps://tambien.bandcamp.com/track/descomposicion-iv-triple-n\n\n\nSUPPORT THE SHOW!\nhttps://loveandradio.org/member\n\n\n\u00a1SECRETOS EN ESPA\u00d1OL!\nhttps://canalconfidente.org\nSee Privacy Policy at https://art19.com/privacy and California Privacy Notice at https://art19.com/privacy#do-not-sell-my-info.",
            "contentSnippet": "LEAVE A SECRET!\nVisit https://secretshotline.org or call 1-929-SECRETS\n\n\nMUSIC!\nhttps://tambien.bandcamp.com/track/l-grimas-de-sangre-ii\nhttps://ab-isikkural.bandcamp.com/track/winter-in-a-cassette\nhttps://tambien.bandcamp.com/album/las-olas\nhttps://tambien.bandcamp.com/track/descomposicion-iv-triple-n\n\n\nSUPPORT THE SHOW!\nhttps://loveandradio.org/member\n\n\n\u00a1SECRETOS EN ESPA\u00d1OL!\nhttps://canalconfidente.org\nSee Privacy Policy at https://art19.com/privacy and California Privacy Notice at https://art19.com/privacy#do-not-sell-my-info.",
            "enclosure": {
                "length": "16625580",
                "type": "audio/mpeg",
                "url": "https://2.gum.fm/rss.art19.com/episodes/b12fdf29-233d-49d0-a8c7-c12df78dc8a9.mp3?rss_browser=BAhJIg9yc3MtcGFyc2VyBjoGRVQ%3D--42d668516e215326a0c0e36404173d504b339a70"
            },
            "guid": "gid://art19-episode-locator/V0/xt09a9TWZP8A2eimlgblwZ4reC5VeGwkQT41IjXUn1Y",
            "isoDate": "2023-08-11T12:51:01.000Z",
            "itunes": {
                "duration": "00:17:19",
                "episode": "50",
                "episodeType": "full",
                "explicit": "yes",
                "image": "https://content.production.cdn.art19.com/images/bf/04/28/be/bf0428be-c536-4f87-b1a3-044071c2f296/7bee994acbd000f54fdc23688f15800e74a411d9c6473ef8e56b6b20ef5677622e84433d398c845cd38814c7368c56f4b9d9c6b8bd25bfc3950cd3fa37610da4.jpeg",
                "season": "3",
                "summary": "LEAVE A SECRET!\nVisit https://secretshotline.org or call 1-929-SECRETS\n\nMUSIC!\nhttps://tambien.bandcamp.com/track/l-grimas-de-sangre-ii\nhttps://ab-isikkural.bandcamp.com/track/winter-in-a-cassette\nhttps://tambien.bandcamp.com/album/las-olas\nhttps://tambien.bandcamp.com/track/descomposicion-iv-triple-n\n\nSUPPORT THE SHOW!\nhttps://loveandradio.org/member\n\n\u00a1SECRETOS EN ESPA\u00d1OL!\nhttps://canalconfidente.org"
            },
            "link": "https://art19.com/shows/the-secrets-hotline/episodes/b12fdf29-233d-49d0-a8c7-c12df78dc8a9",
            "pubDate": "Fri, 11 Aug 2023 12:51:01 -0000",
            "title": "Giving a Piece of Yourself",
            "entities": {
                "CARDINAL": [
                    "1-929-SECRETSMUSIC!https://tambien.bandcamp.com"
                ],
                "GPE": [
                    "California"
                ]
            }
        },
        {
            "content": "\n        <p>PLAYLIST!</p><p>Wil Bolton - Swept</p><p>Wil Bolton - Going Nowhere</p><p>Nonturn -&nbsp;Gratification</p><p>Ezmeralda - Trocha Triste</p><p><br></p><p>SECRETS!</p><p>929-SECRETS or secretshotline.org</p><p><br></p><p>INSTAGRAM!</p><p>https://instagram.com/thesecretshotline</p><p><br></p><p>SUPPORT THE SHOW (+ EXTRA SECRETS)!</p><p>https://loveandradio.org/member</p><p>See Privacy Policy at <a href=\"https://art19.com/privacy\" rel=\"noopener noreferrer\" target=\"_blank\">https://art19.com/privacy</a> and California Privacy Notice at <a href=\"https://art19.com/privacy#do-not-sell-my-info\" rel=\"noopener noreferrer\" target=\"_blank\">https://art19.com/privacy#do-not-sell-my-info</a>.</p>\n      ",
            "content:encoded": "\n        <p>PLAYLIST!</p><p>Wil Bolton - Swept</p><p>Wil Bolton - Going Nowhere</p><p>Nonturn -&nbsp;Gratification</p><p>Ezmeralda - Trocha Triste</p><p><br></p><p>SECRETS!</p><p>929-SECRETS or secretshotline.org</p><p><br></p><p>INSTAGRAM!</p><p>https://instagram.com/thesecretshotline</p><p><br></p><p>SUPPORT THE SHOW (+ EXTRA SECRETS)!</p><p>https://loveandradio.org/member</p><p>See Privacy Policy at <a href=\"https://art19.com/privacy\" rel=\"noopener noreferrer\" target=\"_blank\">https://art19.com/privacy</a> and California Privacy Notice at <a href=\"https://art19.com/privacy#do-not-sell-my-info\" rel=\"noopener noreferrer\" target=\"_blank\">https://art19.com/privacy#do-not-sell-my-info</a>.</p>\n      ",
            "content:encodedSnippet": "PLAYLIST!\nWil Bolton - Swept\nWil Bolton - Going Nowhere\nNonturn -\u00a0Gratification\nEzmeralda - Trocha Triste\n\n\nSECRETS!\n929-SECRETS or secretshotline.org\n\n\nINSTAGRAM!\nhttps://instagram.com/thesecretshotline\n\n\nSUPPORT THE SHOW (+ EXTRA SECRETS)!\nhttps://loveandradio.org/member\nSee Privacy Policy at https://art19.com/privacy and California Privacy Notice at https://art19.com/privacy#do-not-sell-my-info.",
            "contentSnippet": "PLAYLIST!\nWil Bolton - Swept\nWil Bolton - Going Nowhere\nNonturn -\u00a0Gratification\nEzmeralda - Trocha Triste\n\n\nSECRETS!\n929-SECRETS or secretshotline.org\n\n\nINSTAGRAM!\nhttps://instagram.com/thesecretshotline\n\n\nSUPPORT THE SHOW (+ EXTRA SECRETS)!\nhttps://loveandradio.org/member\nSee Privacy Policy at https://art19.com/privacy and California Privacy Notice at https://art19.com/privacy#do-not-sell-my-info.",
            "enclosure": {
                "length": "17623666",
                "type": "audio/mpeg",
                "url": "https://2.gum.fm/rss.art19.com/episodes/aaab2e78-dd20-45b6-913e-724ad484582d.mp3?rss_browser=BAhJIg9yc3MtcGFyc2VyBjoGRVQ%3D--42d668516e215326a0c0e36404173d504b339a70"
            },
            "guid": "gid://art19-episode-locator/V0/Zn1VgsmSmMgnF3hBnCv4a14-tYe3uXlgZL-P1aChl_c",
            "isoDate": "2023-07-28T14:00:00.000Z",
            "itunes": {
                "duration": "00:18:21",
                "episode": "49",
                "episodeType": "full",
                "explicit": "yes",
                "image": "https://content.production.cdn.art19.com/images/bf/04/28/be/bf0428be-c536-4f87-b1a3-044071c2f296/7bee994acbd000f54fdc23688f15800e74a411d9c6473ef8e56b6b20ef5677622e84433d398c845cd38814c7368c56f4b9d9c6b8bd25bfc3950cd3fa37610da4.jpeg",
                "season": "3",
                "summary": "PLAYLIST!\nWil Bolton - Swept\nWil Bolton - Going Nowhere\nNonturn -  Gratification\nEzmeralda - Trocha Triste\n\nSECRETS!\n929-SECRETS or secretshotline.org\n\nINSTAGRAM!\nhttps://instagram.com/thesecretshotline\n\nSUPPORT THE SHOW (+ EXTRA SECRETS)!\nhttps://loveandradio.org/member"
            },
            "link": "https://art19.com/shows/the-secrets-hotline/episodes/aaab2e78-dd20-45b6-913e-724ad484582d",
            "pubDate": "Fri, 28 Jul 2023 14:00:00 -0000",
            "title": "Knowing and Doing",
            "entities": {
                "PERSON": [
                    "PLAYLIST!Wil Bolton - SweptWil"
                ],
                "ORG": [
                    "Bolton - Going NowhereNonturn -\u00a0",
                    "GratificationEzmeralda"
                ],
                "GPE": [
                    "California"
                ]
            }
        },
        {
            "content": "\n        <p>PLAYLIST!</p><p>Wil Bolton - Bindweed</p><p>Wil Bolton - Points of Light</p><p>Isik Kural - Rosemary</p><p>Zoroxxe - Paisaje Oblicuo</p><p><br></p><p>SECRETS!</p><p>929-SECRETS or secretshotline.org</p><p><br></p><p>INSTAGRAM!</p><p>https://instagram.com/thesecretshotline</p><p><br></p><p>EXTRA SECRETS!</p><p>https://loveandradio.org/member</p><p>See Privacy Policy at <a href=\"https://art19.com/privacy\" rel=\"noopener noreferrer\" target=\"_blank\">https://art19.com/privacy</a> and California Privacy Notice at <a href=\"https://art19.com/privacy#do-not-sell-my-info\" rel=\"noopener noreferrer\" target=\"_blank\">https://art19.com/privacy#do-not-sell-my-info</a>.</p>\n      ",
            "content:encoded": "\n        <p>PLAYLIST!</p><p>Wil Bolton - Bindweed</p><p>Wil Bolton - Points of Light</p><p>Isik Kural - Rosemary</p><p>Zoroxxe - Paisaje Oblicuo</p><p><br></p><p>SECRETS!</p><p>929-SECRETS or secretshotline.org</p><p><br></p><p>INSTAGRAM!</p><p>https://instagram.com/thesecretshotline</p><p><br></p><p>EXTRA SECRETS!</p><p>https://loveandradio.org/member</p><p>See Privacy Policy at <a href=\"https://art19.com/privacy\" rel=\"noopener noreferrer\" target=\"_blank\">https://art19.com/privacy</a> and California Privacy Notice at <a href=\"https://art19.com/privacy#do-not-sell-my-info\" rel=\"noopener noreferrer\" target=\"_blank\">https://art19.com/privacy#do-not-sell-my-info</a>.</p>\n      ",
            "content:encodedSnippet": "PLAYLIST!\nWil Bolton - Bindweed\nWil Bolton - Points of Light\nIsik Kural - Rosemary\nZoroxxe - Paisaje Oblicuo\n\n\nSECRETS!\n929-SECRETS or secretshotline.org\n\n\nINSTAGRAM!\nhttps://instagram.com/thesecretshotline\n\n\nEXTRA SECRETS!\nhttps://loveandradio.org/member\nSee Privacy Policy at https://art19.com/privacy and California Privacy Notice at https://art19.com/privacy#do-not-sell-my-info.",
            "contentSnippet": "PLAYLIST!\nWil Bolton - Bindweed\nWil Bolton - Points of Light\nIsik Kural - Rosemary\nZoroxxe - Paisaje Oblicuo\n\n\nSECRETS!\n929-SECRETS or secretshotline.org\n\n\nINSTAGRAM!\nhttps://instagram.com/thesecretshotline\n\n\nEXTRA SECRETS!\nhttps://loveandradio.org/member\nSee Privacy Policy at https://art19.com/privacy and California Privacy Notice at https://art19.com/privacy#do-not-sell-my-info.",
            "enclosure": {
                "length": "14855523",
                "type": "audio/mpeg",
                "url": "https://2.gum.fm/rss.art19.com/episodes/8a226d0d-4868-4eed-b0be-ad9fe4610bf6.mp3?rss_browser=BAhJIg9yc3MtcGFyc2VyBjoGRVQ%3D--42d668516e215326a0c0e36404173d504b339a70"
            },
            "guid": "gid://art19-episode-locator/V0/ZBImwIOHmnU_6xBiWde2XEkgckypyTk1-S1bFCwgb6Q",
            "isoDate": "2023-07-21T16:58:18.000Z",
            "itunes": {
                "duration": "00:15:28",
                "episode": "48",
                "episodeType": "full",
                "explicit": "yes",
                "image": "https://content.production.cdn.art19.com/images/bf/04/28/be/bf0428be-c536-4f87-b1a3-044071c2f296/7bee994acbd000f54fdc23688f15800e74a411d9c6473ef8e56b6b20ef5677622e84433d398c845cd38814c7368c56f4b9d9c6b8bd25bfc3950cd3fa37610da4.jpeg",
                "season": "3",
                "summary": "929-SECRETS"
            },
            "link": "https://art19.com/shows/the-secrets-hotline/episodes/8a226d0d-4868-4eed-b0be-ad9fe4610bf6",
            "pubDate": "Fri, 21 Jul 2023 16:58:18 -0000",
            "title": "Existential Expiration",
            "entities": {
                "PERSON": [
                    "PLAYLIST!Wil Bolton - BindweedWil"
                ],
                "ORG": [
                    "Bolton - Points of LightIsik Kural - RosemaryZoroxxe - Paisaje"
                ],
                "GPE": [
                    "California"
                ]
            }
        },
        {
            "content": "\n        <p>PLAYLIST!</p><p>https://quixosis.bandcamp.com/track/descomposici-n-2-stillness</p><p>https://tambien.bandcamp.com/track/v-rtigo</p><p>https://quixosis.bandcamp.com/track/buenas-noches-imposible</p><p>https://quixosis.bandcamp.com/track/cascada</p><p>https://tambien.bandcamp.com/track/calima</p><p><br></p><p>CALL WITH YOUR SECRET!</p><p>929-SECRETS or secretshotline.org</p><p><br></p><p>SUPPORT THE SHOW!</p><p>https://loveandradio.org/member</p><p>See Privacy Policy at <a href=\"https://art19.com/privacy\" rel=\"noopener noreferrer\" target=\"_blank\">https://art19.com/privacy</a> and California Privacy Notice at <a href=\"https://art19.com/privacy#do-not-sell-my-info\" rel=\"noopener noreferrer\" target=\"_blank\">https://art19.com/privacy#do-not-sell-my-info</a>.</p>\n      ",
            "content:encoded": "\n        <p>PLAYLIST!</p><p>https://quixosis.bandcamp.com/track/descomposici-n-2-stillness</p><p>https://tambien.bandcamp.com/track/v-rtigo</p><p>https://quixosis.bandcamp.com/track/buenas-noches-imposible</p><p>https://quixosis.bandcamp.com/track/cascada</p><p>https://tambien.bandcamp.com/track/calima</p><p><br></p><p>CALL WITH YOUR SECRET!</p><p>929-SECRETS or secretshotline.org</p><p><br></p><p>SUPPORT THE SHOW!</p><p>https://loveandradio.org/member</p><p>See Privacy Policy at <a href=\"https://art19.com/privacy\" rel=\"noopener noreferrer\" target=\"_blank\">https://art19.com/privacy</a> and California Privacy Notice at <a href=\"https://art19.com/privacy#do-not-sell-my-info\" rel=\"noopener noreferrer\" target=\"_blank\">https://art19.com/privacy#do-not-sell-my-info</a>.</p>\n      ",
            "content:encodedSnippet": "PLAYLIST!\nhttps://quixosis.bandcamp.com/track/descomposici-n-2-stillness\nhttps://tambien.bandcamp.com/track/v-rtigo\nhttps://quixosis.bandcamp.com/track/buenas-noches-imposible\nhttps://quixosis.bandcamp.com/track/cascada\nhttps://tambien.bandcamp.com/track/calima\n\n\nCALL WITH YOUR SECRET!\n929-SECRETS or secretshotline.org\n\n\nSUPPORT THE SHOW!\nhttps://loveandradio.org/member\nSee Privacy Policy at https://art19.com/privacy and California Privacy Notice at https://art19.com/privacy#do-not-sell-my-info.",
            "contentSnippet": "PLAYLIST!\nhttps://quixosis.bandcamp.com/track/descomposici-n-2-stillness\nhttps://tambien.bandcamp.com/track/v-rtigo\nhttps://quixosis.bandcamp.com/track/buenas-noches-imposible\nhttps://quixosis.bandcamp.com/track/cascada\nhttps://tambien.bandcamp.com/track/calima\n\n\nCALL WITH YOUR SECRET!\n929-SECRETS or secretshotline.org\n\n\nSUPPORT THE SHOW!\nhttps://loveandradio.org/member\nSee Privacy Policy at https://art19.com/privacy and California Privacy Notice at https://art19.com/privacy#do-not-sell-my-info.",
            "enclosure": {
                "length": "16787748",
                "type": "audio/mpeg",
                "url": "https://2.gum.fm/rss.art19.com/episodes/fe3f6d00-d59f-418a-baa4-8ee5e3ed74cf.mp3?rss_browser=BAhJIg9yc3MtcGFyc2VyBjoGRVQ%3D--42d668516e215326a0c0e36404173d504b339a70"
            },
            "guid": "gid://art19-episode-locator/V0/IWQyOIAZSr58ZyNr6r2y-7RmPVhyrQhpxvoSEqR0Wh4",
            "isoDate": "2023-07-14T13:30:00.000Z",
            "itunes": {
                "duration": "00:17:29",
                "episode": "47",
                "episodeType": "full",
                "explicit": "yes",
                "image": "https://content.production.cdn.art19.com/images/bf/04/28/be/bf0428be-c536-4f87-b1a3-044071c2f296/7bee994acbd000f54fdc23688f15800e74a411d9c6473ef8e56b6b20ef5677622e84433d398c845cd38814c7368c56f4b9d9c6b8bd25bfc3950cd3fa37610da4.jpeg",
                "season": "3",
                "summary": "Call 929-SECRETS or visit secretshotline.org"
            },
            "link": "https://art19.com/shows/the-secrets-hotline/episodes/fe3f6d00-d59f-418a-baa4-8ee5e3ed74cf",
            "pubDate": "Fri, 14 Jul 2023 13:30:00 -0000",
            "title": "COVID Be Damned I'm Gonna Get Some",
            "entities": {
                "GPE": [
                    "California"
                ]
            }
        },
        {
            "content": "\n        <p>Your dreams, remixed.</p><p><br></p><p>MUSIC AND SOUND DESIGN BY AUTISTICI!</p><p>https://autistici.bandcamp.com/music</p><p><br></p><p>LEAVE A SECRET/DREAM/SECRET DREAM!</p><p>929-SECRETS or secretshotline.org</p><p><br></p><p>SUPPORT THE SHOW!</p><p>https://loveandradio.org/member</p><p>See Privacy Policy at <a href=\"https://art19.com/privacy\" rel=\"noopener noreferrer\" target=\"_blank\">https://art19.com/privacy</a> and California Privacy Notice at <a href=\"https://art19.com/privacy#do-not-sell-my-info\" rel=\"noopener noreferrer\" target=\"_blank\">https://art19.com/privacy#do-not-sell-my-info</a>.</p>\n      ",
            "content:encoded": "\n        <p>Your dreams, remixed.</p><p><br></p><p>MUSIC AND SOUND DESIGN BY AUTISTICI!</p><p>https://autistici.bandcamp.com/music</p><p><br></p><p>LEAVE A SECRET/DREAM/SECRET DREAM!</p><p>929-SECRETS or secretshotline.org</p><p><br></p><p>SUPPORT THE SHOW!</p><p>https://loveandradio.org/member</p><p>See Privacy Policy at <a href=\"https://art19.com/privacy\" rel=\"noopener noreferrer\" target=\"_blank\">https://art19.com/privacy</a> and California Privacy Notice at <a href=\"https://art19.com/privacy#do-not-sell-my-info\" rel=\"noopener noreferrer\" target=\"_blank\">https://art19.com/privacy#do-not-sell-my-info</a>.</p>\n      ",
            "content:encodedSnippet": "Your dreams, remixed.\n\n\nMUSIC AND SOUND DESIGN BY AUTISTICI!\nhttps://autistici.bandcamp.com/music\n\n\nLEAVE A SECRET/DREAM/SECRET DREAM!\n929-SECRETS or secretshotline.org\n\n\nSUPPORT THE SHOW!\nhttps://loveandradio.org/member\nSee Privacy Policy at https://art19.com/privacy and California Privacy Notice at https://art19.com/privacy#do-not-sell-my-info.",
            "contentSnippet": "Your dreams, remixed.\n\n\nMUSIC AND SOUND DESIGN BY AUTISTICI!\nhttps://autistici.bandcamp.com/music\n\n\nLEAVE A SECRET/DREAM/SECRET DREAM!\n929-SECRETS or secretshotline.org\n\n\nSUPPORT THE SHOW!\nhttps://loveandradio.org/member\nSee Privacy Policy at https://art19.com/privacy and California Privacy Notice at https://art19.com/privacy#do-not-sell-my-info.",
            "enclosure": {
                "length": "19734360",
                "type": "audio/mpeg",
                "url": "https://2.gum.fm/rss.art19.com/episodes/3d3fe865-e52b-457c-972c-f1b65017dc70.mp3?rss_browser=BAhJIg9yc3MtcGFyc2VyBjoGRVQ%3D--42d668516e215326a0c0e36404173d504b339a70"
            },
            "guid": "gid://art19-episode-locator/V0/3-PZ7IXMHmLKvj3GjkPtzxgAhwosiVAZ6y14l-fSiug",
            "isoDate": "2023-07-07T16:55:36.000Z",
            "itunes": {
                "duration": "00:20:33",
                "episode": "46",
                "episodeType": "full",
                "explicit": "yes",
                "image": "https://content.production.cdn.art19.com/images/bf/04/28/be/bf0428be-c536-4f87-b1a3-044071c2f296/7bee994acbd000f54fdc23688f15800e74a411d9c6473ef8e56b6b20ef5677622e84433d398c845cd38814c7368c56f4b9d9c6b8bd25bfc3950cd3fa37610da4.jpeg",
                "season": "3",
                "summary": "Your dreams, remixed."
            },
            "link": "https://art19.com/shows/the-secrets-hotline/episodes/3d3fe865-e52b-457c-972c-f1b65017dc70",
            "pubDate": "Fri, 07 Jul 2023 16:55:36 -0000",
            "title": "Dreamworld",
            "entities": {
                "PERSON": [
                    "DREAM!929-SECRETS"
                ],
                "GPE": [
                    "California"
                ]
            }
        },
        {
            "content": "\n        <p>The forbidden allure of fairly mid but kind of good chicken.</p><p><br></p><p>PLAYLIST!</p><p>https://jimmybehan.bandcamp.com/track/rust</p><p>https://jimmybehan.bandcamp.com/track/dusk</p><p>https://cue-shop.bandcamp.com/</p><p><br></p><p>LEAVE A SECRET!</p><p>https://secretshotline.org</p><p>or 929-SECRETS</p><p><br></p><p>SUPPORT THE SHOW!</p><p>https://loveandradio.org/member</p><p>See Privacy Policy at <a href=\"https://art19.com/privacy\" rel=\"noopener noreferrer\" target=\"_blank\">https://art19.com/privacy</a> and California Privacy Notice at <a href=\"https://art19.com/privacy#do-not-sell-my-info\" rel=\"noopener noreferrer\" target=\"_blank\">https://art19.com/privacy#do-not-sell-my-info</a>.</p>\n      ",
            "content:encoded": "\n        <p>The forbidden allure of fairly mid but kind of good chicken.</p><p><br></p><p>PLAYLIST!</p><p>https://jimmybehan.bandcamp.com/track/rust</p><p>https://jimmybehan.bandcamp.com/track/dusk</p><p>https://cue-shop.bandcamp.com/</p><p><br></p><p>LEAVE A SECRET!</p><p>https://secretshotline.org</p><p>or 929-SECRETS</p><p><br></p><p>SUPPORT THE SHOW!</p><p>https://loveandradio.org/member</p><p>See Privacy Policy at <a href=\"https://art19.com/privacy\" rel=\"noopener noreferrer\" target=\"_blank\">https://art19.com/privacy</a> and California Privacy Notice at <a href=\"https://art19.com/privacy#do-not-sell-my-info\" rel=\"noopener noreferrer\" target=\"_blank\">https://art19.com/privacy#do-not-sell-my-info</a>.</p>\n      ",
            "content:encodedSnippet": "The forbidden allure of fairly mid but kind of good chicken.\n\n\nPLAYLIST!\nhttps://jimmybehan.bandcamp.com/track/rust\nhttps://jimmybehan.bandcamp.com/track/dusk\nhttps://cue-shop.bandcamp.com/\n\n\nLEAVE A SECRET!\nhttps://secretshotline.org\nor 929-SECRETS\n\n\nSUPPORT THE SHOW!\nhttps://loveandradio.org/member\nSee Privacy Policy at https://art19.com/privacy and California Privacy Notice at https://art19.com/privacy#do-not-sell-my-info.",
            "contentSnippet": "The forbidden allure of fairly mid but kind of good chicken.\n\n\nPLAYLIST!\nhttps://jimmybehan.bandcamp.com/track/rust\nhttps://jimmybehan.bandcamp.com/track/dusk\nhttps://cue-shop.bandcamp.com/\n\n\nLEAVE A SECRET!\nhttps://secretshotline.org\nor 929-SECRETS\n\n\nSUPPORT THE SHOW!\nhttps://loveandradio.org/member\nSee Privacy Policy at https://art19.com/privacy and California Privacy Notice at https://art19.com/privacy#do-not-sell-my-info.",
            "enclosure": {
                "length": "14649469",
                "type": "audio/mpeg",
                "url": "https://2.gum.fm/rss.art19.com/episodes/5da55b3c-b3c6-4552-823e-687f6b2393b0.mp3?rss_browser=BAhJIg9yc3MtcGFyc2VyBjoGRVQ%3D--42d668516e215326a0c0e36404173d504b339a70"
            },
            "guid": "gid://art19-episode-locator/V0/qmVX6w0kCAT8TyAECICOEkcKZj5EpboaxhzAmP10QpU",
            "isoDate": "2023-06-29T20:00:00.000Z",
            "itunes": {
                "duration": "00:15:15",
                "episode": "45",
                "episodeType": "full",
                "explicit": "yes",
                "image": "https://content.production.cdn.art19.com/images/bf/04/28/be/bf0428be-c536-4f87-b1a3-044071c2f296/7bee994acbd000f54fdc23688f15800e74a411d9c6473ef8e56b6b20ef5677622e84433d398c845cd38814c7368c56f4b9d9c6b8bd25bfc3950cd3fa37610da4.jpeg",
                "season": "3",
                "summary": "The forbidden allure of fairly mid but kind of good chicken."
            },
            "link": "https://art19.com/shows/the-secrets-hotline/episodes/5da55b3c-b3c6-4552-823e-687f6b2393b0",
            "pubDate": "Thu, 29 Jun 2023 20:00:00 -0000",
            "title": "Nosey With Purpose",
            "entities": {
                "CARDINAL": [
                    "929"
                ],
                "GPE": [
                    "California"
                ]
            }
        },
        {
            "content": "\n        <p>(Specifically, Mister Rogers)</p><p><br></p><p>PLAYLIST!</p><p>https://audiobulb.bandcamp.com/track/lost-light</p><p>https://audiobulb.bandcamp.com/track/uno</p><p>https://audiobulb.bandcamp.com/track/one-dimensional-personality-tv-characters-working-in-our-home-office</p><p>https://eileanrec.bandcamp.com/album/a-year-at-ushers-hill</p><p><br></p><p>EXTRA SECRETS!</p><p>https://loveandradio.org/member</p><p><br></p><p>LEAVE A SECRET!</p><p>929-SECRETS or secretshotline.org</p><p>See Privacy Policy at <a href=\"https://art19.com/privacy\" rel=\"noopener noreferrer\" target=\"_blank\">https://art19.com/privacy</a> and California Privacy Notice at <a href=\"https://art19.com/privacy#do-not-sell-my-info\" rel=\"noopener noreferrer\" target=\"_blank\">https://art19.com/privacy#do-not-sell-my-info</a>.</p>\n      ",
            "content:encoded": "\n        <p>(Specifically, Mister Rogers)</p><p><br></p><p>PLAYLIST!</p><p>https://audiobulb.bandcamp.com/track/lost-light</p><p>https://audiobulb.bandcamp.com/track/uno</p><p>https://audiobulb.bandcamp.com/track/one-dimensional-personality-tv-characters-working-in-our-home-office</p><p>https://eileanrec.bandcamp.com/album/a-year-at-ushers-hill</p><p><br></p><p>EXTRA SECRETS!</p><p>https://loveandradio.org/member</p><p><br></p><p>LEAVE A SECRET!</p><p>929-SECRETS or secretshotline.org</p><p>See Privacy Policy at <a href=\"https://art19.com/privacy\" rel=\"noopener noreferrer\" target=\"_blank\">https://art19.com/privacy</a> and California Privacy Notice at <a href=\"https://art19.com/privacy#do-not-sell-my-info\" rel=\"noopener noreferrer\" target=\"_blank\">https://art19.com/privacy#do-not-sell-my-info</a>.</p>\n      ",
            "content:encodedSnippet": "(Specifically, Mister Rogers)\n\n\nPLAYLIST!\nhttps://audiobulb.bandcamp.com/track/lost-light\nhttps://audiobulb.bandcamp.com/track/uno\nhttps://audiobulb.bandcamp.com/track/one-dimensional-personality-tv-characters-working-in-our-home-office\nhttps://eileanrec.bandcamp.com/album/a-year-at-ushers-hill\n\n\nEXTRA SECRETS!\nhttps://loveandradio.org/member\n\n\nLEAVE A SECRET!\n929-SECRETS or secretshotline.org\nSee Privacy Policy at https://art19.com/privacy and California Privacy Notice at https://art19.com/privacy#do-not-sell-my-info.",
            "contentSnippet": "(Specifically, Mister Rogers)\n\n\nPLAYLIST!\nhttps://audiobulb.bandcamp.com/track/lost-light\nhttps://audiobulb.bandcamp.com/track/uno\nhttps://audiobulb.bandcamp.com/track/one-dimensional-personality-tv-characters-working-in-our-home-office\nhttps://eileanrec.bandcamp.com/album/a-year-at-ushers-hill\n\n\nEXTRA SECRETS!\nhttps://loveandradio.org/member\n\n\nLEAVE A SECRET!\n929-SECRETS or secretshotline.org\nSee Privacy Policy at https://art19.com/privacy and California Privacy Notice at https://art19.com/privacy#do-not-sell-my-info.",
            "enclosure": {
                "length": "14610599",
                "type": "audio/mpeg",
                "url": "https://2.gum.fm/rss.art19.com/episodes/c5ee0c4d-8d9a-43f8-be08-6d36f8e2afc4.mp3?rss_browser=BAhJIg9yc3MtcGFyc2VyBjoGRVQ%3D--42d668516e215326a0c0e36404173d504b339a70"
            },
            "guid": "gid://art19-episode-locator/V0/bwRTwjqC--IN06qzbGZnmx9blJh9I7aMPv16eh2rK8E",
            "isoDate": "2023-06-22T16:00:00.000Z",
            "itunes": {
                "duration": "00:15:13",
                "episode": "44",
                "episodeType": "full",
                "explicit": "yes",
                "image": "https://content.production.cdn.art19.com/images/bf/04/28/be/bf0428be-c536-4f87-b1a3-044071c2f296/7bee994acbd000f54fdc23688f15800e74a411d9c6473ef8e56b6b20ef5677622e84433d398c845cd38814c7368c56f4b9d9c6b8bd25bfc3950cd3fa37610da4.jpeg",
                "season": "3",
                "summary": "(Specifically, Mister Rogers)"
            },
            "link": "https://art19.com/shows/the-secrets-hotline/episodes/c5ee0c4d-8d9a-43f8-be08-6d36f8e2afc4",
            "pubDate": "Thu, 22 Jun 2023 16:00:00 -0000",
            "title": "Somebody to Love You",
            "entities": {
                "GPE": [
                    "California"
                ]
            }
        },
        {
            "content": "\n        <p>Listeners wrestle with questions about past sexual trauma.</p><p><br></p><p>Playlist:</p><p>https://ab-jimmybehan.bandcamp.com/album/the-echo-garden</p><p>https://cue-shop.bandcamp.com/track/whidbey-island-afternoon</p><p>https://tambien.bandcamp.com/track/alb-n</p><p><br></p><p>Call:</p><p>929-SECRETS or secretshotline.org</p><p><br></p><p>Support:</p><p>https://loveandradio.org/member</p><p>See Privacy Policy at <a href=\"https://art19.com/privacy\" rel=\"noopener noreferrer\" target=\"_blank\">https://art19.com/privacy</a> and California Privacy Notice at <a href=\"https://art19.com/privacy#do-not-sell-my-info\" rel=\"noopener noreferrer\" target=\"_blank\">https://art19.com/privacy#do-not-sell-my-info</a>.</p>\n      ",
            "content:encoded": "\n        <p>Listeners wrestle with questions about past sexual trauma.</p><p><br></p><p>Playlist:</p><p>https://ab-jimmybehan.bandcamp.com/album/the-echo-garden</p><p>https://cue-shop.bandcamp.com/track/whidbey-island-afternoon</p><p>https://tambien.bandcamp.com/track/alb-n</p><p><br></p><p>Call:</p><p>929-SECRETS or secretshotline.org</p><p><br></p><p>Support:</p><p>https://loveandradio.org/member</p><p>See Privacy Policy at <a href=\"https://art19.com/privacy\" rel=\"noopener noreferrer\" target=\"_blank\">https://art19.com/privacy</a> and California Privacy Notice at <a href=\"https://art19.com/privacy#do-not-sell-my-info\" rel=\"noopener noreferrer\" target=\"_blank\">https://art19.com/privacy#do-not-sell-my-info</a>.</p>\n      ",
            "content:encodedSnippet": "Listeners wrestle with questions about past sexual trauma.\n\n\nPlaylist:\nhttps://ab-jimmybehan.bandcamp.com/album/the-echo-garden\nhttps://cue-shop.bandcamp.com/track/whidbey-island-afternoon\nhttps://tambien.bandcamp.com/track/alb-n\n\n\nCall:\n929-SECRETS or secretshotline.org\n\n\nSupport:\nhttps://loveandradio.org/member\nSee Privacy Policy at https://art19.com/privacy and California Privacy Notice at https://art19.com/privacy#do-not-sell-my-info.",
            "contentSnippet": "Listeners wrestle with questions about past sexual trauma.\n\n\nPlaylist:\nhttps://ab-jimmybehan.bandcamp.com/album/the-echo-garden\nhttps://cue-shop.bandcamp.com/track/whidbey-island-afternoon\nhttps://tambien.bandcamp.com/track/alb-n\n\n\nCall:\n929-SECRETS or secretshotline.org\n\n\nSupport:\nhttps://loveandradio.org/member\nSee Privacy Policy at https://art19.com/privacy and California Privacy Notice at https://art19.com/privacy#do-not-sell-my-info.",
            "enclosure": {
                "length": "17289299",
                "type": "audio/mpeg",
                "url": "https://2.gum.fm/rss.art19.com/episodes/2ed937d8-ea9c-46f9-b284-4ef2a8da2c09.mp3?rss_browser=BAhJIg9yc3MtcGFyc2VyBjoGRVQ%3D--42d668516e215326a0c0e36404173d504b339a70"
            },
            "guid": "gid://art19-episode-locator/V0/XnS72tk0V8t0xCrvuvmG16D00I-k93Whr1FLTm1yyoY",
            "isoDate": "2023-06-15T13:00:00.000Z",
            "itunes": {
                "duration": "00:18:00",
                "episode": "43",
                "episodeType": "full",
                "explicit": "yes",
                "image": "https://content.production.cdn.art19.com/images/bf/04/28/be/bf0428be-c536-4f87-b1a3-044071c2f296/7bee994acbd000f54fdc23688f15800e74a411d9c6473ef8e56b6b20ef5677622e84433d398c845cd38814c7368c56f4b9d9c6b8bd25bfc3950cd3fa37610da4.jpeg",
                "season": "3",
                "summary": "Listeners wrestle with questions about past sexual trauma."
            },
            "link": "https://art19.com/shows/the-secrets-hotline/episodes/2ed937d8-ea9c-46f9-b284-4ef2a8da2c09",
            "pubDate": "Thu, 15 Jun 2023 13:00:00 -0000",
            "title": "Hard Memories",
            "entities": {
                "PERSON": [
                    "https://ab-jimmybehan.bandcamp.com"
                ],
                "GPE": [
                    "California"
                ]
            }
        },
        {
            "content": "\n        <p>A caller accidentally makes herself racist, one bong hit solves a world of problems, what to do when a stranger makes incidental contact on the bus, and more!</p><p>PLAYLIST!</p><p>https://nonturn.bandcamp.com/track/abandon</p><p>https://ab-jimmybehan.bandcamp.com/track/clock-for-no-time</p><p>https://samarecordings.bandcamp.com/track/quixosis-deshilache</p><p><br></p><p>SECRETS!</p><p>929-SECRETS or https://secretshotline.org</p><p><br></p><p>SUPPORT!</p><p>https://loveandradio.org/member</p><p><br></p><p>\u00a1SECRETOS EN ESPA\u00d1OL!</p><p>https://canalconfidente.org/</p><p><br></p><p>See Privacy Policy at <a href=\"https://art19.com/privacy\" rel=\"noopener noreferrer\" target=\"_blank\">https://art19.com/privacy</a> and California Privacy Notice at <a href=\"https://art19.com/privacy#do-not-sell-my-info\" rel=\"noopener noreferrer\" target=\"_blank\">https://art19.com/privacy#do-not-sell-my-info</a>.</p>\n      ",
            "content:encoded": "\n        <p>A caller accidentally makes herself racist, one bong hit solves a world of problems, what to do when a stranger makes incidental contact on the bus, and more!</p><p>PLAYLIST!</p><p>https://nonturn.bandcamp.com/track/abandon</p><p>https://ab-jimmybehan.bandcamp.com/track/clock-for-no-time</p><p>https://samarecordings.bandcamp.com/track/quixosis-deshilache</p><p><br></p><p>SECRETS!</p><p>929-SECRETS or https://secretshotline.org</p><p><br></p><p>SUPPORT!</p><p>https://loveandradio.org/member</p><p><br></p><p>\u00a1SECRETOS EN ESPA\u00d1OL!</p><p>https://canalconfidente.org/</p><p><br></p><p>See Privacy Policy at <a href=\"https://art19.com/privacy\" rel=\"noopener noreferrer\" target=\"_blank\">https://art19.com/privacy</a> and California Privacy Notice at <a href=\"https://art19.com/privacy#do-not-sell-my-info\" rel=\"noopener noreferrer\" target=\"_blank\">https://art19.com/privacy#do-not-sell-my-info</a>.</p>\n      ",
            "content:encodedSnippet": "A caller accidentally makes herself racist, one bong hit solves a world of problems, what to do when a stranger makes incidental contact on the bus, and more!\nPLAYLIST!\nhttps://nonturn.bandcamp.com/track/abandon\nhttps://ab-jimmybehan.bandcamp.com/track/clock-for-no-time\nhttps://samarecordings.bandcamp.com/track/quixosis-deshilache\n\n\nSECRETS!\n929-SECRETS or https://secretshotline.org\n\n\nSUPPORT!\nhttps://loveandradio.org/member\n\n\n\u00a1SECRETOS EN ESPA\u00d1OL!\nhttps://canalconfidente.org/\n\n\nSee Privacy Policy at https://art19.com/privacy and California Privacy Notice at https://art19.com/privacy#do-not-sell-my-info.",
            "contentSnippet": "A caller accidentally makes herself racist, one bong hit solves a world of problems, what to do when a stranger makes incidental contact on the bus, and more!\nPLAYLIST!\nhttps://nonturn.bandcamp.com/track/abandon\nhttps://ab-jimmybehan.bandcamp.com/track/clock-for-no-time\nhttps://samarecordings.bandcamp.com/track/quixosis-deshilache\n\n\nSECRETS!\n929-SECRETS or https://secretshotline.org\n\n\nSUPPORT!\nhttps://loveandradio.org/member\n\n\n\u00a1SECRETOS EN ESPA\u00d1OL!\nhttps://canalconfidente.org/\n\n\nSee Privacy Policy at https://art19.com/privacy and California Privacy Notice at https://art19.com/privacy#do-not-sell-my-info.",
            "enclosure": {
                "length": "16524852",
                "type": "audio/mpeg",
                "url": "https://2.gum.fm/rss.art19.com/episodes/2add9c48-0e02-4ac6-bdd2-d37f6f390c3a.mp3?rss_browser=BAhJIg9yc3MtcGFyc2VyBjoGRVQ%3D--42d668516e215326a0c0e36404173d504b339a70"
            },
            "guid": "gid://art19-episode-locator/V0/F7uOPvidInY0QhyJOo5IOF6CO7PTwRhx9BFDW7hXjts",
            "isoDate": "2023-06-09T19:00:00.000Z",
            "itunes": {
                "duration": "00:17:12",
                "episode": "42",
                "episodeType": "full",
                "explicit": "yes",
                "image": "https://content.production.cdn.art19.com/images/bf/04/28/be/bf0428be-c536-4f87-b1a3-044071c2f296/7bee994acbd000f54fdc23688f15800e74a411d9c6473ef8e56b6b20ef5677622e84433d398c845cd38814c7368c56f4b9d9c6b8bd25bfc3950cd3fa37610da4.jpeg",
                "season": "3",
                "summary": "A caller accidentally makes herself racist, one bong hit solves a world of problems, what to do when a stranger makes incidental contact on the bus, and more!"
            },
            "link": "https://art19.com/shows/the-secrets-hotline/episodes/2add9c48-0e02-4ac6-bdd2-d37f6f390c3a",
            "pubDate": "Fri, 09 Jun 2023 19:00:00 -0000",
            "title": "Giving It Another Go",
            "entities": {
                "CARDINAL": [
                    "one"
                ],
                "GPE": [
                    "https://secretshotline.orgSUPPORT!https://loveandradio.org",
                    "California"
                ]
            }
        }
    ],
    "itunes": {
        "author": "Love and Radio",
        "categories": [
            "Society & Culture"
        ],
        "categoriesWithSubs": [
            {
                "name": "Society & Culture",
                "subs": null
            }
        ],
        "explicit": "yes",
        "image": "https://content.production.cdn.art19.com/images/bf/04/28/be/bf0428be-c536-4f87-b1a3-044071c2f296/7bee994acbd000f54fdc23688f15800e74a411d9c6473ef8e56b6b20ef5677622e84433d398c845cd38814c7368c56f4b9d9c6b8bd25bfc3950cd3fa37610da4.jpeg",
        "owner": {
            "email": "contact@secretshotline.org",
            "name": "Love and Radio"
        },
        "summary": "\n      What\u2019s your secret? Listen as anonymous callers from across the globe share what is hidden in their lives. It\u2019s both a voyeuristic and affirming experience.\u00a0Leave your own at 1-929-SECRETS (929-732-7387) or\u00a0secretshotline.org.\n    "
    },
    "language": "en",
    "link": "https://secretshotline.org",
    "managingEditor": "contact@secretshotline.org (Love and Radio)",
    "paginationLinks": {
        "self": "https://rss.art19.com/the-secrets-hotline"
    },
    "palette": [
        "400A4C",
        "EBDBED",
        "81248F",
        "B17EB8",
        "70158F",
        "9D59B4"
    ],
    "title": "The Secrets Hotline",
    "entities": {
        "CARDINAL": [
            "1-929-SECRETS",
            "929-732-7387"
        ]
    }
}